{"text_boxes":[{"id":1,"bbox":[322,30,355,42],"text":"Belize"},{"id":2,"bbox":[322,44,357,56],"text":"90596"},{"id":3,"bbox":[322,58,394,70],"text":"Schwaebisch "},{"id":4,"bbox":[394,58,415,70],"text":"Hall"},{"id":5,"bbox":[322,72,344,84],"text":"Am "},{"id":6,"bbox":[344,72,363,84],"text":"Hof"},{"id":7,"bbox":[30,116,65,127],"text":"Burkina "},{"id":8,"bbox":[65,116,84,127],"text":"Faso"},{"id":9,"bbox":[30,128,55,139],"text":"90602"},{"id":10,"bbox":[30,140,77,151],"text":"Ravensburg"},{"id":11,"bbox":[30,152,78,163],"text":"Dietrichweg"},{"id":12,"bbox":[30,30,83,44],"text":"Acterna "},{"id":13,"bbox":[83,30,117,44],"text":"Corp."},{"id":14,"bbox":[30,169,43,184],"text":"C. "},{"id":15,"bbox":[43,169,57,184],"text":"H. "},{"id":16,"bbox":[57,169,110,184],"text":"Robinson "},{"id":17,"bbox":[110,169,174,184],"text":"Worldwide "},{"id":18,"bbox":[174,169,192,184],"text":"Inc."},{"id":19,"bbox":[30,214,44,226],"text":"Bill:"},{"id":20,"bbox":[30,232,282,246],"text":"8c65aa1e-e14d-48f7-9c25-0fc1e2e09a5c"},{"id":21,"bbox":[491,232,555,244],"text":"08.03.2008"},{"id":22,"bbox":[30,276,52,289],"text":"Unit"},{"id":23,"bbox":[205,276,224,289],"text":"Qty"},{"id":24,"bbox":[380,276,408,289],"text":"Total"},{"id":25,"bbox":[30,305,107,317],"text":"Sqmmxxubdktw"},{"id":26,"bbox":[205,305,232,317],"text":"5,490"},{"id":27,"bbox":[380,305,407,317],"text":"7,988"},{"id":28,"bbox":[30,328,95,340],"text":"Xvhyiktpqxoo"},{"id":29,"bbox":[205,328,232,340],"text":"2,816"},{"id":30,"bbox":[380,328,407,340],"text":"4,265"},{"id":31,"bbox":[30,351,91,363],"text":"Atvdmfyjbrlo"},{"id":32,"bbox":[205,351,232,363],"text":"8,052"},{"id":33,"bbox":[380,351,407,363],"text":"6,701"},{"id":34,"bbox":[30,374,106,386],"text":"Pvemqrdbdbow"},{"id":35,"bbox":[205,374,232,386],"text":"0,806"},{"id":36,"bbox":[380,374,407,386],"text":"3,751"},{"id":37,"bbox":[30,397,100,409],"text":"Botmvfdboaax"},{"id":38,"bbox":[205,397,232,409],"text":"5,987"},{"id":39,"bbox":[380,397,407,409],"text":"6,238"},{"id":40,"bbox":[443,439,474,452],"text":"Total "},{"id":41,"bbox":[474,439,507,452],"text":"(AOA)"},{"id":42,"bbox":[517,439,555,452],"text":"37,152"}],"fields":[{"field_name":"SENDER_ADDRESS","value_id":[1,2,3,4,5,6],"value_text":"Belize 90596 Schwaebisch Hall Am Hof","key_id":[],"key_text":[]},{"field_name":"RECEIVER_ADDRESS","value_id":[7,8,9,10,11],"value_text":"Burkina Faso 90602 Ravensburg Dietrichweg","key_id":[],"key_text":[]},{"field_name":"SENDER_NAME","value_id":[12,13],"value_text":"Acterna Corp.","key_id":[],"key_text":[]},{"field_name":"RECEIVER_NAME","value_id":[14,15,16,17,18],"value_text":"C. H. Robinson Worldwide Inc.","key_id":[],"key_text":[]},{"field_name":"INVOICE_NUMBER","value_id":[20],"value_text":"8c65aa1e-e14d-48f7-9c25-0fc1e2e09a5c","key_id":[],"key_text":[]},{"field_name":"INVOICE_DATE","value_id":[21],"value_text":"08.03.2008","key_id":[],"key_text":[]},{"field_name":"TOTAL_AMOUNT","value_id":[42],"value_text":"37,152","key_id":[],"key_text":[]}],"global_attributes": {"file_id":"20220224_585_451_124.png"}}