{"text_boxes":[{"id":1,"bbox":[327,30,368,43],"text":"England "},{"id":2,"bbox":[368,30,401,43],"text":"90475 "},{"id":3,"bbox":[401,30,446,43],"text":"Bruchsal "},{"id":4,"bbox":[446,30,522,43],"text":"Diepeschrather "},{"id":5,"bbox":[522,30,539,43],"text":"Str."},{"id":6,"bbox":[30,75,97,88],"text":"Mozambique "},{"id":7,"bbox":[97,75,130,88],"text":"89520 "},{"id":8,"bbox":[130,75,185,88],"text":"Mannheim "},{"id":9,"bbox":[185,75,206,88],"text":"Am "},{"id":10,"bbox":[206,75,253,88],"text":"Haelentor"},{"id":11,"bbox":[327,50,371,64],"text":"Astoria "},{"id":12,"bbox":[371,50,425,64],"text":"Financial "},{"id":13,"bbox":[425,50,491,64],"text":"Corporation"},{"id":14,"bbox":[327,75,393,90],"text":"Anthem, "},{"id":15,"bbox":[393,75,421,90],"text":"Inc."},{"id":16,"bbox":[30,120,72,134],"text":"Invoice:"},{"id":17,"bbox":[82,120,275,133],"text":"25896f0f-a4b2-4e34-a126-dcf315f6e061"},{"id":18,"bbox":[511,120,565,133],"text":"20.08.2001"},{"id":19,"bbox":[30,164,62,178],"text":"Type"},{"id":20,"bbox":[208,164,246,178],"text":"Count"},{"id":21,"bbox":[386,164,421,178],"text":"Item "},{"id":22,"bbox":[421,164,450,178],"text":"Sum"},{"id":23,"bbox":[30,195,103,208],"text":"Oerrjpvjpcrk"},{"id":24,"bbox":[208,195,240,208],"text":"3,184"},{"id":25,"bbox":[386,195,418,208],"text":"9,188"},{"id":26,"bbox":[30,220,110,233],"text":"Ymqkehxpffrp"},{"id":27,"bbox":[208,220,240,233],"text":"0,120"},{"id":28,"bbox":[386,220,418,233],"text":"3,989"},{"id":29,"bbox":[465,263,493,277],"text":"Total "},{"id":30,"bbox":[493,263,522,277],"text":"(GBP)"},{"id":31,"bbox":[532,263,565,277],"text":"63,393"}],"fields":[{"field_name":"SENDER_ADDRESS","value_id":[1,2,3,4,5],"value_text":"England 90475 Bruchsal Diepeschrather Str.","key_id":[],"key_text":[]},{"field_name":"RECEIVER_ADDRESS","value_id":[6,7,8,9,10],"value_text":"Mozambique 89520 Mannheim Am Haelentor","key_id":[],"key_text":[]},{"field_name":"SENDER_NAME","value_id":[11,12,13],"value_text":"Astoria Financial Corporation","key_id":[],"key_text":[]},{"field_name":"RECEIVER_NAME","value_id":[14,15],"value_text":"Anthem, Inc.","key_id":[],"key_text":[]},{"field_name":"INVOICE_NUMBER","value_id":[17],"value_text":"25896f0f-a4b2-4e34-a126-dcf315f6e061","key_id":[],"key_text":[]},{"field_name":"INVOICE_DATE","value_id":[18],"value_text":"20.08.2001","key_id":[],"key_text":[]},{"field_name":"TOTAL_AMOUNT","value_id":[31],"value_text":"63,393","key_id":[],"key_text":[]}],"global_attributes": {"file_id":"20220224_595_842_71.png"}}