{"text_boxes":[{"id":1,"bbox":[327,30,349,42],"text":"Cabo "},{"id":2,"bbox":[349,30,373,42],"text":"Verde"},{"id":3,"bbox":[327,43,352,55],"text":"90530"},{"id":4,"bbox":[327,56,344,68],"text":"Bad "},{"id":5,"bbox":[344,56,399,68],"text":"Mergentheim"},{"id":6,"bbox":[327,69,344,81],"text":"bul. "},{"id":7,"bbox":[344,69,376,81],"text":"Bulgaria"},{"id":8,"bbox":[327,112,371,123],"text":"Cambodia "},{"id":9,"bbox":[371,112,399,123],"text":"89522 "},{"id":10,"bbox":[399,112,433,123],"text":"London "},{"id":11,"bbox":[433,112,451,123],"text":"Am "},{"id":12,"bbox":[451,112,483,123],"text":"Höfchen"},{"id":13,"bbox":[327,87,356,101],"text":"Bell "},{"id":14,"bbox":[356,87,449,101],"text":"Microproducts "},{"id":15,"bbox":[449,87,472,101],"text":"Inc."},{"id":16,"bbox":[327,129,372,143],"text":"Autoliv, "},{"id":17,"bbox":[372,129,392,143],"text":"Inc."},{"id":18,"bbox":[30,173,51,185],"text":"Bill:"},{"id":19,"bbox":[61,173,293,186],"text":"822b2f83-bf14-496c-9948-a1c3d9dee2e5"},{"id":20,"bbox":[519,173,565,185],"text":"19.04.2006"},{"id":21,"bbox":[30,216,61,229],"text":"Name"},{"id":22,"bbox":[163,216,186,229],"text":"Unit"},{"id":23,"bbox":[296,216,334,229],"text":"Single "},{"id":24,"bbox":[334,216,364,229],"text":"Price "},{"id":25,"bbox":[364,216,395,229],"text":"(EUR)"},{"id":26,"bbox":[429,216,460,229],"text":"Total "},{"id":27,"bbox":[460,216,487,229],"text":"Item "},{"id":28,"bbox":[487,216,514,229],"text":"Price"},{"id":29,"bbox":[30,246,93,258],"text":"Zdeczhfgvxvi"},{"id":30,"bbox":[163,246,219,258],"text":"Zggziiicevio"},{"id":31,"bbox":[296,246,323,258],"text":"6,225"},{"id":32,"bbox":[429,246,456,258],"text":"2,943"},{"id":33,"bbox":[30,269,99,281],"text":"Kdtqofkmdbgw"},{"id":34,"bbox":[163,269,228,281],"text":"Lfqidtqovhmu"},{"id":35,"bbox":[296,269,323,281],"text":"1,228"},{"id":36,"bbox":[429,269,456,281],"text":"5,258"},{"id":37,"bbox":[30,292,95,304],"text":"Yeoqyncbwjbf"},{"id":38,"bbox":[163,292,224,304],"text":"Smadrujvyrln"},{"id":39,"bbox":[296,292,323,304],"text":"8,026"},{"id":40,"bbox":[429,292,456,304],"text":"8,921"},{"id":41,"bbox":[30,315,97,327],"text":"Dhxcxxvtqquz"},{"id":42,"bbox":[163,315,222,327],"text":"Ngozsiwyilpi"},{"id":43,"bbox":[296,315,323,327],"text":"4,823"},{"id":44,"bbox":[429,315,456,327],"text":"5,931"},{"id":45,"bbox":[30,338,95,350],"text":"Yxlmonfrerry"},{"id":46,"bbox":[163,338,231,350],"text":"Qnxuvwxnlbcg"},{"id":47,"bbox":[296,338,323,350],"text":"8,560"},{"id":48,"bbox":[429,338,456,350],"text":"0,423"},{"id":49,"bbox":[376,380,429,394],"text":"Invoice "},{"id":50,"bbox":[429,380,462,394],"text":"Sum "},{"id":51,"bbox":[462,380,503,394],"text":"(EUR)"},{"id":52,"bbox":[513,380,565,394],"text":"832,168"}],"fields":[{"field_name":"SENDER_ADDRESS","value_id":[1,2,3,4,5,6,7],"value_text":"Cabo Verde 90530 Bad Mergentheim bul. Bulgaria","key_id":[],"key_text":[]},{"field_name":"RECEIVER_ADDRESS","value_id":[8,9,10,11,12],"value_text":"Cambodia 89522 London Am Höfchen","key_id":[],"key_text":[]},{"field_name":"SENDER_NAME","value_id":[13,14,15],"value_text":"Bell Microproducts Inc.","key_id":[],"key_text":[]},{"field_name":"RECEIVER_NAME","value_id":[16,17],"value_text":"Autoliv, Inc.","key_id":[],"key_text":[]},{"field_name":"INVOICE_NUMBER","value_id":[19],"value_text":"822b2f83-bf14-496c-9948-a1c3d9dee2e5","key_id":[],"key_text":[]},{"field_name":"INVOICE_DATE","value_id":[20],"value_text":"19.04.2006","key_id":[],"key_text":[]},{"field_name":"TOTAL_AMOUNT","value_id":[52],"value_text":"832,168","key_id":[],"key_text":[]}],"global_attributes": {"file_id":"20220212_116.png"}}