{"text_boxes":[{"id":1,"text":"Ghana","bbox":[327,26,30,12]},{"id":2,"text":"T-1000","bbox":[327,28,43,12]},{"id":3,"text":"Dortmund","bbox":[327,40,56,12]},{"id":4,"text":"Parkway ","bbox":[327,37,69,12]},{"id":5,"text":"Mountain ","bbox":[364,41,69,12]},{"id":6,"text":"View","bbox":[405,20,69,12]},{"id":7,"text":"England","bbox":[30,32,112,12]},{"id":8,"text":"11235813","bbox":[30,40,125,12]},{"id":9,"text":"Bonn","bbox":[30,20,138,12]},{"id":10,"text":"bul. ","bbox":[30,17,151,12]},{"id":11,"text":"Bulgaria","bbox":[47,32,151,12]},{"id":12,"text":"Adesso ","bbox":[30,42,30,15]},{"id":13,"text":"SE","bbox":[72,12,30,15]},{"id":14,"text":"Big ","bbox":[30,23,169,14]},{"id":15,"text":"O ","bbox":[53,13,169,14]},{"id":16,"text":"Notation ","bbox":[66,49,169,14]},{"id":17,"text":"Incorporated","bbox":[115,69,169,14]},{"id":18,"text":"Bill:","bbox":[30,14,213,12]},{"id":19,"text":"4c0156de-b507-4fba-a3dd-d1d9c74ead20","bbox":[30,201,231,13]},{"id":20,"text":"01.11.2003","bbox":[501,64,231,12]},{"id":21,"text":"Name","bbox":[30,38,274,14]},{"id":22,"text":"Single ","bbox":[208,45,274,14]},{"id":23,"text":"Price ","bbox":[253,38,274,14]},{"id":24,"text":"(EUR)","bbox":[291,41,274,14]},{"id":25,"text":"Total","bbox":[386,33,274,14]},{"id":26,"text":"Xcedrgdvggvj","bbox":[30,79,305,13]},{"id":27,"text":"7,690","bbox":[208,32,305,13]},{"id":28,"text":"9,492","bbox":[386,32,305,13]},{"id":29,"text":"Nrwnuxxjwwtl","bbox":[30,79,330,13]},{"id":30,"text":"8,489","bbox":[208,32,330,13]},{"id":31,"text":"8,357","bbox":[386,32,330,13]},{"id":32,"text":"Xsxuuymeugkj","bbox":[30,85,355,13]},{"id":33,"text":"9,462","bbox":[208,32,355,13]},{"id":34,"text":"6,434","bbox":[386,32,355,13]},{"id":35,"text":"Txxsvtlrbvjv","bbox":[30,71,380,13]},{"id":36,"text":"6,373","bbox":[208,32,380,13]},{"id":37,"text":"7,889","bbox":[386,32,380,13]},{"id":38,"text":"Bzpivhmfrwuo","bbox":[30,81,405,13]},{"id":39,"text":"3,702","bbox":[208,32,405,13]},{"id":40,"text":"7,669","bbox":[386,32,405,13]},{"id":41,"text":"Nbhkpymqgqim","bbox":[30,89,430,13]},{"id":42,"text":"7,083","bbox":[208,32,430,13]},{"id":43,"text":"9,813","bbox":[386,32,430,13]},{"id":44,"text":"Fvxklrjvjmmg","bbox":[30,79,455,13]},{"id":45,"text":"8,425","bbox":[208,32,455,13]},{"id":46,"text":"7,394","bbox":[386,32,455,13]},{"id":47,"text":"Motymkwkrero","bbox":[30,85,480,13]},{"id":48,"text":"3,762","bbox":[208,32,480,13]},{"id":49,"text":"8,170","bbox":[386,32,480,13]},{"id":50,"text":"Total ","bbox":[448,31,523,13]},{"id":51,"text":"(EUR)","bbox":[479,31,523,13]},{"id":52,"text":"697,661","bbox":[520,45,523,13]}],"fields":[{"field_name":"SENDER_ADDRESS","value_id":[1,2,3,4,5,6],"value_text":"Ghana T-1000 Dortmund Parkway Mountain View","key_id":[],"key_text":[]},{"field_name":"RECEIVER_ADDRESS","value_id":[7,8,9,10,11],"value_text":"England 11235813 Bonn bul. Bulgaria","key_id":[],"key_text":[]},{"field_name":"SENDER_NAME","value_id":[12,13],"value_text":"Adesso SE","key_id":[],"key_text":[]},{"field_name":"RECEIVER_NAME","value_id":[14,15,16,17],"value_text":"Big O Notation Incorporated","key_id":[],"key_text":[]},{"field_name":"INVOICE_NUMBER","value_id":[19],"value_text":"4c0156de-b507-4fba-a3dd-d1d9c74ead20","key_id":[],"key_text":[]},{"field_name":"INVOICE_DATE","value_id":[20],"value_text":"01.11.2003","key_id":[],"key_text":[]},{"field_name":"TOTAL_AMOUNT","value_id":[52],"value_text":"697,661","key_id":[],"key_text":[]}],"global_attributes": {"file_id":"20211221_42.png"}}