{"text_boxes":[{"id":1,"text":"Mozambique","bbox":[327,52,30,11]},{"id":2,"text":"11235813","bbox":[327,40,42,11]},{"id":3,"text":"Plovdiv","bbox":[327,32,54,11]},{"id":4,"text":"bul. ","bbox":[327,19,66,11]},{"id":5,"text":"Bulgaria","bbox":[346,34,66,11]},{"id":6,"text":"Bulgaria","bbox":[327,34,108,11]},{"id":7,"text":"491625","bbox":[327,30,120,11]},{"id":8,"text":"Bonn","bbox":[327,22,132,11]},{"id":9,"text":"Parkway ","bbox":[327,37,144,11]},{"id":10,"text":"Mountain ","bbox":[364,42,144,11]},{"id":11,"text":"View","bbox":[406,21,144,11]},{"id":12,"text":"Adesso ","bbox":[327,42,83,15]},{"id":13,"text":"Bulgaria ","bbox":[369,46,83,15]},{"id":14,"text":"EOOD","bbox":[415,32,83,15]},{"id":15,"text":"Tarzan ","bbox":[327,53,161,15]},{"id":16,"text":"OOD","bbox":[380,32,161,15]},{"id":17,"text":"Invoice:","bbox":[30,32,206,11]},{"id":18,"text":"7a14233b-6e59-4e4b-989a-a50ca751b2d2","bbox":[72,242,206,13]},{"id":19,"text":"25.01.2010","bbox":[519,46,206,12]},{"id":20,"text":"Item","bbox":[30,23,249,14]},{"id":21,"text":"Type","bbox":[163,24,249,14]},{"id":22,"text":"Qty","bbox":[296,18,249,14]},{"id":23,"text":"Total ","bbox":[429,28,249,14]},{"id":24,"text":"Item ","bbox":[457,26,249,14]},{"id":25,"text":"Price","bbox":[483,24,249,14]},{"id":26,"text":"Qkihfododcus","bbox":[30,64,279,13]},{"id":27,"text":"Swwlfdmgcsyj","bbox":[163,65,279,13]},{"id":28,"text":"7,784","bbox":[296,27,279,13]},{"id":29,"text":"7,484","bbox":[429,27,279,13]},{"id":30,"text":"Jktaoewjcxuj","bbox":[30,61,304,13]},{"id":31,"text":"Xonsxfstoasa","bbox":[163,63,304,13]},{"id":32,"text":"4,095","bbox":[296,27,304,13]},{"id":33,"text":"1,977","bbox":[429,27,304,13]},{"id":34,"text":"Invoice ","bbox":[30,38,347,14]},{"id":35,"text":"Sum ","bbox":[68,25,347,14]},{"id":36,"text":"(EUR)","bbox":[93,29,347,14]},{"id":37,"text":"478,068","bbox":[132,39,347,14]}],"fields":[{"field_name":"SENDER_ADDRESS","value_id":[1,2,3,4,5],"value_text":"Mozambique 11235813 Plovdiv bul. Bulgaria","key_id":[],"key_text":[]},{"field_name":"RECEIVER_ADDRESS","value_id":[6,7,8,9,10,11],"value_text":"Bulgaria 491625 Bonn Parkway Mountain View","key_id":[],"key_text":[]},{"field_name":"SENDER_NAME","value_id":[12,13,14],"value_text":"Adesso Bulgaria EOOD","key_id":[],"key_text":[]},{"field_name":"RECEIVER_NAME","value_id":[15,16],"value_text":"Tarzan OOD","key_id":[],"key_text":[]},{"field_name":"INVOICE_NUMBER","value_id":[18],"value_text":"7a14233b-6e59-4e4b-989a-a50ca751b2d2","key_id":[],"key_text":[]},{"field_name":"INVOICE_DATE","value_id":[19],"value_text":"25.01.2010","key_id":[],"key_text":[]},{"field_name":"TOTAL_AMOUNT","value_id":[37],"value_text":"478,068","key_id":[],"key_text":[]}],"global_attributes": {"file_id":"20211221_166.png"}}