{"text_boxes":[{"id":1,"text":"England ","bbox":[327,34,30,12]},{"id":2,"text":"T-1000 ","bbox":[361,30,30,12]},{"id":3,"text":"Berlin ","bbox":[391,24,30,12]},{"id":4,"text":"The ","bbox":[415,17,30,12]},{"id":5,"text":"Street","bbox":[432,24,30,12]},{"id":6,"text":"England ","bbox":[327,43,73,11]},{"id":7,"text":"D-51149 ","bbox":[370,43,73,11]},{"id":8,"text":"Plovdiv ","bbox":[413,38,73,11]},{"id":9,"text":"The ","bbox":[451,22,73,11]},{"id":10,"text":"Street","bbox":[473,28,73,11]},{"id":11,"text":"Tarzan ","bbox":[30,38,30,15]},{"id":12,"text":"OOD","bbox":[68,26,30,15]},{"id":13,"text":"Big ","bbox":[327,23,91,14]},{"id":14,"text":"O ","bbox":[350,13,91,14]},{"id":15,"text":"Notation ","bbox":[363,49,91,14]},{"id":16,"text":"Incorporated","bbox":[412,69,91,14]},{"id":17,"text":"Invoice:","bbox":[30,45,135,12]},{"id":18,"text":"0d6e1bce-fb6d-4f2d-be8d-150620d684f3","bbox":[85,201,135,14]},{"id":19,"text":"26.07.2018","bbox":[501,64,135,12]},{"id":20,"text":"Quantity","bbox":[30,48,179,13]},{"id":21,"text":"Unit ","bbox":[208,26,179,13]},{"id":22,"text":"Price ","bbox":[234,30,179,13]},{"id":23,"text":"(USD)","bbox":[264,33,179,13]},{"id":24,"text":"Total","bbox":[386,28,179,13]},{"id":25,"text":"7,874","bbox":[30,27,209,12]},{"id":26,"text":"1,453","bbox":[208,27,209,12]},{"id":27,"text":"5,112","bbox":[386,27,209,12]},{"id":28,"text":"7,301","bbox":[30,27,232,12]},{"id":29,"text":"8,479","bbox":[208,27,232,12]},{"id":30,"text":"0,019","bbox":[386,27,232,12]},{"id":31,"text":"3,803","bbox":[30,27,255,12]},{"id":32,"text":"9,977","bbox":[208,27,255,12]},{"id":33,"text":"1,445","bbox":[386,27,255,12]},{"id":34,"text":"9,064","bbox":[30,27,278,12]},{"id":35,"text":"0,439","bbox":[208,27,278,12]},{"id":36,"text":"9,442","bbox":[386,27,278,12]},{"id":37,"text":"1,193","bbox":[30,27,301,12]},{"id":38,"text":"4,599","bbox":[208,27,301,12]},{"id":39,"text":"8,738","bbox":[386,27,301,12]},{"id":40,"text":"8,034","bbox":[30,27,324,12]},{"id":41,"text":"6,545","bbox":[208,27,324,12]},{"id":42,"text":"6,924","bbox":[386,27,324,12]},{"id":43,"text":"Invoice ","bbox":[30,40,366,13]},{"id":44,"text":"Sum ","bbox":[70,28,366,13]},{"id":45,"text":"(BGN)","bbox":[98,34,366,13]},{"id":46,"text":"598,956","bbox":[142,39,366,13]}],"fields":[{"field_name":"SENDER_ADDRESS","value_id":[1,2,3,4,5],"value_text":"England T-1000 Berlin The Street","key_id":[],"key_text":[]},{"field_name":"RECEIVER_ADDRESS","value_id":[6,7,8,9,10],"value_text":"England D-51149 Plovdiv The Street","key_id":[],"key_text":[]},{"field_name":"SENDER_NAME","value_id":[11,12],"value_text":"Tarzan OOD","key_id":[],"key_text":[]},{"field_name":"RECEIVER_NAME","value_id":[13,14,15,16],"value_text":"Big O Notation Incorporated","key_id":[],"key_text":[]},{"field_name":"INVOICE_NUMBER","value_id":[18],"value_text":"0d6e1bce-fb6d-4f2d-be8d-150620d684f3","key_id":[],"key_text":[]},{"field_name":"INVOICE_DATE","value_id":[19],"value_text":"26.07.2018","key_id":[],"key_text":[]},{"field_name":"TOTAL_AMOUNT","value_id":[46],"value_text":"598,956","key_id":[],"key_text":[]}],"global_attributes": {"file_id":"20220117_1549.png"}}