{"text_boxes":[{"id":1,"text":"England ","bbox":[30,35,30,10]},{"id":2,"text":"11235813 ","bbox":[65,42,30,10]},{"id":3,"text":"Sofia ","bbox":[107,21,30,10]},{"id":4,"text":"Tzar ","bbox":[128,18,30,10]},{"id":5,"text":"Boris","bbox":[146,21,30,10]},{"id":6,"text":"Deutschland ","bbox":[30,49,71,10]},{"id":7,"text":"T-1000 ","bbox":[79,29,71,10]},{"id":8,"text":"Sofia ","bbox":[108,20,71,10]},{"id":9,"text":"Tzar ","bbox":[128,17,71,10]},{"id":10,"text":"Boris","bbox":[145,19,71,10]},{"id":11,"text":"Adesso ","bbox":[30,49,46,14]},{"id":12,"text":"SE","bbox":[79,17,46,14]},{"id":13,"text":"Zero ","bbox":[327,37,71,15]},{"id":14,"text":"Overhead ","bbox":[364,75,71,15]},{"id":15,"text":"Industries ","bbox":[439,78,71,15]},{"id":16,"text":"SE","bbox":[517,18,71,15]},{"id":17,"text":"Receipt:","bbox":[30,35,116,10]},{"id":18,"text":"2c0d8013-5773-4880-8d96-486769d10bbc","bbox":[75,206,116,14]},{"id":19,"text":"06.01.2002","bbox":[503,62,116,10]},{"id":20,"text":"Name","bbox":[30,38,160,14]},{"id":21,"text":"Price ","bbox":[208,38,160,14]},{"id":22,"text":"(EUR)","bbox":[246,41,160,14]},{"id":23,"text":"Item ","bbox":[386,35,160,14]},{"id":24,"text":"Sum","bbox":[421,29,160,14]},{"id":25,"text":"Prnkfrodqwyt","bbox":[30,76,191,13]},{"id":26,"text":"7,388","bbox":[208,32,191,13]},{"id":27,"text":"9,664","bbox":[386,32,191,13]},{"id":28,"text":"Fpthmzubivlm","bbox":[30,79,216,13]},{"id":29,"text":"5,528","bbox":[208,32,216,13]},{"id":30,"text":"1,202","bbox":[386,32,216,13]},{"id":31,"text":"Azwqvruhrbqe","bbox":[30,82,241,13]},{"id":32,"text":"5,394","bbox":[208,32,241,13]},{"id":33,"text":"4,047","bbox":[386,32,241,13]},{"id":34,"text":"Ltzqmzkescld","bbox":[30,76,266,13]},{"id":35,"text":"7,537","bbox":[208,32,266,13]},{"id":36,"text":"5,181","bbox":[386,32,266,13]},{"id":37,"text":"Jnrptzwxinjg","bbox":[30,71,291,13]},{"id":38,"text":"8,489","bbox":[208,32,291,13]},{"id":39,"text":"4,062","bbox":[386,32,291,13]},{"id":40,"text":"Shcizdqkkhsq","bbox":[30,78,316,13]},{"id":41,"text":"4,070","bbox":[208,32,316,13]},{"id":42,"text":"1,427","bbox":[386,32,316,13]},{"id":43,"text":"Kaxylvfxisnr","bbox":[30,71,341,13]},{"id":44,"text":"9,082","bbox":[208,32,341,13]},{"id":45,"text":"3,347","bbox":[386,32,341,13]},{"id":46,"text":"Udjgbtjxwcxv","bbox":[30,77,366,13]},{"id":47,"text":"5,316","bbox":[208,32,366,13]},{"id":48,"text":"1,500","bbox":[386,32,366,13]},{"id":49,"text":"Xziyngfvgqyd","bbox":[30,77,391,13]},{"id":50,"text":"2,273","bbox":[208,32,391,13]},{"id":51,"text":"3,136","bbox":[386,32,391,13]},{"id":52,"text":"Invoice ","bbox":[30,43,434,13]},{"id":53,"text":"Sum ","bbox":[73,29,434,13]},{"id":54,"text":"(USD)","bbox":[102,32,434,13]},{"id":55,"text":"222,273","bbox":[144,45,434,13]}],"fields":[{"field_name":"SENDER_ADDRESS","value_id":[1,2,3,4,5],"value_text":"England 11235813 Sofia Tzar Boris","key_id":[],"key_text":[]},{"field_name":"RECEIVER_ADDRESS","value_id":[6,7,8,9,10],"value_text":"Deutschland T-1000 Sofia Tzar Boris","key_id":[],"key_text":[]},{"field_name":"SENDER_NAME","value_id":[11,12],"value_text":"Adesso SE","key_id":[],"key_text":[]},{"field_name":"RECEIVER_NAME","value_id":[13,14,15,16],"value_text":"Zero Overhead Industries SE","key_id":[],"key_text":[]},{"field_name":"INVOICE_NUMBER","value_id":[18],"value_text":"2c0d8013-5773-4880-8d96-486769d10bbc","key_id":[],"key_text":[]},{"field_name":"INVOICE_DATE","value_id":[19],"value_text":"06.01.2002","key_id":[],"key_text":[]},{"field_name":"TOTAL_AMOUNT","value_id":[55],"value_text":"222,273","key_id":[],"key_text":[]}],"global_attributes": {"file_id":"20220117_1602.png"}}