{"text_boxes":[{"id":1,"text":"Mozambique ","bbox":[30,73,30,13]},{"id":2,"text":"D-98693 ","bbox":[103,51,30,13]},{"id":3,"text":"Bonn ","bbox":[154,32,30,13]},{"id":4,"text":"The ","bbox":[186,24,30,13]},{"id":5,"text":"Street","bbox":[210,32,30,13]},{"id":6,"text":"England ","bbox":[293,55,74,14]},{"id":7,"text":"11235813 ","bbox":[348,68,74,14]},{"id":8,"text":"London ","bbox":[416,51,74,14]},{"id":9,"text":"bul. ","bbox":[467,27,74,14]},{"id":10,"text":"Maria ","bbox":[494,38,74,14]},{"id":11,"text":"Luiza","bbox":[532,33,74,14]},{"id":12,"text":"Adesso ","bbox":[30,57,49,15]},{"id":13,"text":"SE","bbox":[87,18,49,15]},{"id":14,"text":"Big ","bbox":[30,23,74,14]},{"id":15,"text":"O ","bbox":[53,13,74,14]},{"id":16,"text":"Notation ","bbox":[66,49,74,14]},{"id":17,"text":"Incorporated","bbox":[115,69,74,14]},{"id":18,"text":"Invoice:","bbox":[30,38,118,13]},{"id":19,"text":"bd65c64c-bef9-4740-a09b-bbd4214792e7","bbox":[78,258,118,14]},{"id":20,"text":"13.07.2004","bbox":[511,54,118,14]},{"id":21,"text":"Qty","bbox":[30,20,162,13]},{"id":22,"text":"Unit","bbox":[163,23,162,13]},{"id":23,"text":"Description","bbox":[296,61,162,13]},{"id":24,"text":"Item ","bbox":[429,27,162,13]},{"id":25,"text":"Sum","bbox":[456,25,162,13]},{"id":26,"text":"9,505","bbox":[30,27,192,12]},{"id":27,"text":"Futkouaxpufr","bbox":[163,62,192,12]},{"id":28,"text":"Rgyolixklvtw","bbox":[296,62,192,12]},{"id":29,"text":"2,919","bbox":[429,27,192,12]},{"id":30,"text":"5,299","bbox":[30,27,215,12]},{"id":31,"text":"Jkogfnxmkbcb","bbox":[163,67,215,12]},{"id":32,"text":"Qswioefmquwv","bbox":[296,69,215,12]},{"id":33,"text":"0,226","bbox":[429,27,215,12]},{"id":34,"text":"2,939","bbox":[30,27,238,12]},{"id":35,"text":"Yjwdmlsuuphw","bbox":[163,68,238,12]},{"id":36,"text":"Yhswropxlrjw","bbox":[296,64,238,12]},{"id":37,"text":"0,543","bbox":[429,27,238,12]},{"id":38,"text":"2,558","bbox":[30,27,261,12]},{"id":39,"text":"Lkywalpgkapb","bbox":[163,67,261,12]},{"id":40,"text":"Vxbgyhkxeawv","bbox":[296,70,261,12]},{"id":41,"text":"5,235","bbox":[429,27,261,12]},{"id":42,"text":"6,796","bbox":[30,27,284,12]},{"id":43,"text":"Ticmcfzzimsx","bbox":[163,66,284,12]},{"id":44,"text":"Rivontrlbbds","bbox":[296,58,284,12]},{"id":45,"text":"8,547","bbox":[429,27,284,12]},{"id":46,"text":"Invoice ","bbox":[30,43,326,13]},{"id":47,"text":"Sum ","bbox":[73,29,326,13]},{"id":48,"text":"(BGN)","bbox":[102,32,326,13]},{"id":49,"text":"762,145","bbox":[144,45,326,13]}],"fields":[{"field_name":"SENDER_ADDRESS","value_id":[1,2,3,4,5],"value_text":"Mozambique D-98693 Bonn The Street","key_id":[],"key_text":[]},{"field_name":"RECEIVER_ADDRESS","value_id":[6,7,8,9,10,11],"value_text":"England 11235813 London bul. Maria Luiza","key_id":[],"key_text":[]},{"field_name":"SENDER_NAME","value_id":[12,13],"value_text":"Adesso SE","key_id":[],"key_text":[]},{"field_name":"RECEIVER_NAME","value_id":[14,15,16,17],"value_text":"Big O Notation Incorporated","key_id":[],"key_text":[]},{"field_name":"INVOICE_NUMBER","value_id":[19],"value_text":"bd65c64c-bef9-4740-a09b-bbd4214792e7","key_id":[],"key_text":[]},{"field_name":"INVOICE_DATE","value_id":[20],"value_text":"13.07.2004","key_id":[],"key_text":[]},{"field_name":"TOTAL_AMOUNT","value_id":[49],"value_text":"762,145","key_id":[],"key_text":[]}],"global_attributes": {"file_id":"20220117_1420.png"}}