{"text_boxes":[{"id":1,"text":"Deutschland","bbox":[30,47,30,10]},{"id":2,"text":"321684","bbox":[30,30,42,10]},{"id":3,"text":"Cologne","bbox":[30,30,54,10]},{"id":4,"text":"bul. ","bbox":[30,16,66,10]},{"id":5,"text":"Maria ","bbox":[46,23,66,10]},{"id":6,"text":"Luiza","bbox":[69,19,66,10]},{"id":7,"text":"Deutschland ","bbox":[327,55,108,10]},{"id":8,"text":"HAL-9000 ","bbox":[382,44,108,10]},{"id":9,"text":"Dortmund ","bbox":[426,44,108,10]},{"id":10,"text":"The ","bbox":[470,18,108,10]},{"id":11,"text":"Street","bbox":[488,25,108,10]},{"id":12,"text":"Adesso ","bbox":[327,42,30,14]},{"id":13,"text":"Bulgaria ","bbox":[369,52,30,14]},{"id":14,"text":"EOOD","bbox":[421,36,30,14]},{"id":15,"text":"Tarzan ","bbox":[327,48,125,14]},{"id":16,"text":"OOD","bbox":[375,29,125,14]},{"id":17,"text":"Receipt:","bbox":[30,29,169,10]},{"id":18,"text":"3515e2e4-42e2-4514-a160-e159b2186876","bbox":[69,270,169,14]},{"id":19,"text":"17.04.2013","bbox":[519,46,169,10]},{"id":20,"text":"Type","bbox":[30,26,213,13]},{"id":21,"text":"Description","bbox":[208,61,213,13]},{"id":22,"text":"Total","bbox":[386,28,213,13]},{"id":23,"text":"Ntbznbficmbe","bbox":[30,64,243,12]},{"id":24,"text":"Nuuwjakkbcnq","bbox":[208,66,243,12]},{"id":25,"text":"0,820","bbox":[386,27,243,12]},{"id":26,"text":"Azolcnnyzgfk","bbox":[30,65,266,12]},{"id":27,"text":"Isyhjgcxifin","bbox":[208,55,266,12]},{"id":28,"text":"7,360","bbox":[386,27,266,12]},{"id":29,"text":"Ixrbdnwnpudc","bbox":[30,64,289,12]},{"id":30,"text":"Asfjehtcnkom","bbox":[208,66,289,12]},{"id":31,"text":"1,226","bbox":[386,27,289,12]},{"id":32,"text":"Qtxdqoshwckc","bbox":[30,67,312,12]},{"id":33,"text":"Hfdzgaxyljed","bbox":[208,60,312,12]},{"id":34,"text":"4,517","bbox":[386,27,312,12]},{"id":35,"text":"Fokzabgilstt","bbox":[30,56,335,12]},{"id":36,"text":"Nyzhxqhajdnp","bbox":[208,67,335,12]},{"id":37,"text":"3,460","bbox":[386,27,335,12]},{"id":38,"text":"Ddadadthtnrj","bbox":[30,60,358,12]},{"id":39,"text":"Qzuzwrzmszud","bbox":[208,67,358,12]},{"id":40,"text":"8,669","bbox":[386,27,358,12]},{"id":41,"text":"Invoice ","bbox":[30,40,400,13]},{"id":42,"text":"Sum ","bbox":[70,28,400,13]},{"id":43,"text":"(USD)","bbox":[98,33,400,13]},{"id":44,"text":"161,980","bbox":[141,39,400,13]}],"fields":[{"field_name":"SENDER_ADDRESS","value_id":[1,2,3,4,5,6],"value_text":"Deutschland 321684 Cologne bul. Maria Luiza","key_id":[],"key_text":[]},{"field_name":"RECEIVER_ADDRESS","value_id":[7,8,9,10,11],"value_text":"Deutschland HAL-9000 Dortmund The Street","key_id":[],"key_text":[]},{"field_name":"SENDER_NAME","value_id":[12,13,14],"value_text":"Adesso Bulgaria EOOD","key_id":[],"key_text":[]},{"field_name":"RECEIVER_NAME","value_id":[15,16],"value_text":"Tarzan OOD","key_id":[],"key_text":[]},{"field_name":"INVOICE_NUMBER","value_id":[18],"value_text":"3515e2e4-42e2-4514-a160-e159b2186876","key_id":[],"key_text":[]},{"field_name":"INVOICE_DATE","value_id":[19],"value_text":"17.04.2013","key_id":[],"key_text":[]},{"field_name":"TOTAL_AMOUNT","value_id":[44],"value_text":"161,980","key_id":[],"key_text":[]}],"global_attributes": {"file_id":"20220117_679.png"}}