{"text_boxes":[{"id":1,"text":"Ghana","bbox":[30,27,30,10]},{"id":2,"text":"321684","bbox":[30,30,42,10]},{"id":3,"text":"New ","bbox":[30,21,54,10]},{"id":4,"text":"York","bbox":[51,20,54,10]},{"id":5,"text":"bul. ","bbox":[30,18,66,10]},{"id":6,"text":"Bulgaria","bbox":[48,33,66,10]},{"id":7,"text":"Ghana","bbox":[327,25,108,10]},{"id":8,"text":"D-98693","bbox":[327,35,119,10]},{"id":9,"text":"New ","bbox":[327,20,130,10]},{"id":10,"text":"York","bbox":[347,20,130,10]},{"id":11,"text":"The ","bbox":[327,16,141,10]},{"id":12,"text":"Street","bbox":[343,22,141,10]},{"id":13,"text":"Tarzan ","bbox":[327,42,30,14]},{"id":14,"text":"OOD","bbox":[369,29,30,14]},{"id":15,"text":"Zero ","bbox":[30,28,108,15]},{"id":16,"text":"Overhead ","bbox":[58,57,108,15]},{"id":17,"text":"Industries ","bbox":[115,57,108,15]},{"id":18,"text":"SE","bbox":[172,12,108,15]},{"id":19,"text":"Bill:","bbox":[30,13,181,10]},{"id":20,"text":"243e7576-1cd9-4db1-8645-fae29a21cbe5","bbox":[30,236,198,13]},{"id":21,"text":"19.11.2007","bbox":[521,44,198,10]},{"id":22,"text":"Quantity","bbox":[30,48,241,13]},{"id":23,"text":"Type","bbox":[163,26,241,13]},{"id":24,"text":"Single ","bbox":[296,38,241,13]},{"id":25,"text":"Price ","bbox":[334,30,241,13]},{"id":26,"text":"(EUR)","bbox":[364,31,241,13]},{"id":27,"text":"Total ","bbox":[429,31,241,13]},{"id":28,"text":"Item ","bbox":[460,27,241,13]},{"id":29,"text":"Price","bbox":[487,27,241,13]},{"id":30,"text":"4,214","bbox":[30,27,271,12]},{"id":31,"text":"Picruwvyulrf","bbox":[163,59,271,12]},{"id":32,"text":"8,034","bbox":[296,27,271,12]},{"id":33,"text":"1,371","bbox":[429,27,271,12]},{"id":34,"text":"0,618","bbox":[30,27,294,12]},{"id":35,"text":"Heflyjalsdvr","bbox":[163,56,294,12]},{"id":36,"text":"3,986","bbox":[296,27,294,12]},{"id":37,"text":"0,353","bbox":[429,27,294,12]},{"id":38,"text":"1,004","bbox":[30,27,317,12]},{"id":39,"text":"Zfgisdluwyvb","bbox":[163,60,317,12]},{"id":40,"text":"4,734","bbox":[296,27,317,12]},{"id":41,"text":"6,653","bbox":[429,27,317,12]},{"id":42,"text":"0,763","bbox":[30,27,340,12]},{"id":43,"text":"Lkockbvxbwqq","bbox":[163,69,340,12]},{"id":44,"text":"3,607","bbox":[296,27,340,12]},{"id":45,"text":"9,309","bbox":[429,27,340,12]},{"id":46,"text":"2,310","bbox":[30,27,363,12]},{"id":47,"text":"Kdmmjvokbunj","bbox":[163,71,363,12]},{"id":48,"text":"8,387","bbox":[296,27,363,12]},{"id":49,"text":"3,516","bbox":[429,27,363,12]},{"id":50,"text":"6,211","bbox":[30,27,386,12]},{"id":51,"text":"Bcpqvhrtuehi","bbox":[163,62,386,12]},{"id":52,"text":"7,348","bbox":[296,27,386,12]},{"id":53,"text":"6,507","bbox":[429,27,386,12]},{"id":54,"text":"Total ","bbox":[433,37,428,14]},{"id":55,"text":"(EUR)","bbox":[470,41,428,14]},{"id":56,"text":"40,534","bbox":[521,44,428,14]}],"fields":[{"field_name":"SENDER_ADDRESS","value_id":[1,2,3,4,5,6],"value_text":"Ghana 321684 New York bul. Bulgaria","key_id":[],"key_text":[]},{"field_name":"RECEIVER_ADDRESS","value_id":[7,8,9,10,11,12],"value_text":"Ghana D-98693 New York The Street","key_id":[],"key_text":[]},{"field_name":"SENDER_NAME","value_id":[13,14],"value_text":"Tarzan OOD","key_id":[],"key_text":[]},{"field_name":"RECEIVER_NAME","value_id":[15,16,17,18],"value_text":"Zero Overhead Industries SE","key_id":[],"key_text":[]},{"field_name":"INVOICE_NUMBER","value_id":[20],"value_text":"243e7576-1cd9-4db1-8645-fae29a21cbe5","key_id":[],"key_text":[]},{"field_name":"INVOICE_DATE","value_id":[21],"value_text":"19.11.2007","key_id":[],"key_text":[]},{"field_name":"TOTAL_AMOUNT","value_id":[56],"value_text":"40,534","key_id":[],"key_text":[]}],"global_attributes": {"file_id":"20220117_657.png"}}