{"text_boxes":[{"id":1,"text":"Mozambique","bbox":[30,70,30,13]},{"id":2,"text":"HAL-9000","bbox":[30,55,44,13]},{"id":3,"text":"Plovdiv","bbox":[30,38,58,13]},{"id":4,"text":"The ","bbox":[30,24,72,13]},{"id":5,"text":"Street","bbox":[54,32,72,13]},{"id":6,"text":"Bulgaria ","bbox":[315,49,116,13]},{"id":7,"text":"HAL-9000 ","bbox":[364,58,116,13]},{"id":8,"text":"Dortmund ","bbox":[422,58,116,13]},{"id":9,"text":"bul. ","bbox":[480,23,116,13]},{"id":10,"text":"Maria ","bbox":[503,33,116,13]},{"id":11,"text":"Luiza","bbox":[536,29,116,13]},{"id":12,"text":"Big ","bbox":[327,23,30,14]},{"id":13,"text":"O ","bbox":[350,13,30,14]},{"id":14,"text":"Notation ","bbox":[363,49,30,14]},{"id":15,"text":"Incorporated","bbox":[412,69,30,14]},{"id":16,"text":"Adesso ","bbox":[315,42,135,14]},{"id":17,"text":"SE","bbox":[357,15,135,14]},{"id":18,"text":"Bill:","bbox":[30,20,179,13]},{"id":19,"text":"4249a3bd-82e4-4a22-abbf-c3fb1c170c00","bbox":[30,233,199,13]},{"id":20,"text":"22.04.2001","bbox":[493,72,199,14]},{"id":21,"text":"Anzahl","bbox":[30,38,243,13]},{"id":22,"text":"Unit","bbox":[163,23,243,13]},{"id":23,"text":"Description","bbox":[296,61,243,13]},{"id":24,"text":"Total ","bbox":[429,31,243,13]},{"id":25,"text":"Item ","bbox":[460,27,243,13]},{"id":26,"text":"Price","bbox":[487,27,243,13]},{"id":27,"text":"0,973","bbox":[30,27,273,12]},{"id":28,"text":"Fshejnjbyywz","bbox":[163,62,273,12]},{"id":29,"text":"Jdtrbpdbrouk","bbox":[296,59,273,12]},{"id":30,"text":"1,046","bbox":[429,27,273,12]},{"id":31,"text":"9,318","bbox":[30,27,296,12]},{"id":32,"text":"Kutaylgsctkp","bbox":[163,61,296,12]},{"id":33,"text":"Meagkqpeqrhg","bbox":[296,67,296,12]},{"id":34,"text":"5,712","bbox":[429,27,296,12]},{"id":35,"text":"Invoice ","bbox":[423,38,338,14]},{"id":36,"text":"Sum ","bbox":[461,25,338,14]},{"id":37,"text":"(USD)","bbox":[486,30,338,14]},{"id":38,"text":"745,089","bbox":[526,39,338,14]}],"fields":[{"field_name":"SENDER_ADDRESS","value_id":[1,2,3,4,5],"value_text":"Mozambique HAL-9000 Plovdiv The Street","key_id":[],"key_text":[]},{"field_name":"RECEIVER_ADDRESS","value_id":[6,7,8,9,10,11],"value_text":"Bulgaria HAL-9000 Dortmund bul. Maria Luiza","key_id":[],"key_text":[]},{"field_name":"SENDER_NAME","value_id":[12,13,14,15],"value_text":"Big O Notation Incorporated","key_id":[],"key_text":[]},{"field_name":"RECEIVER_NAME","value_id":[16,17],"value_text":"Adesso SE","key_id":[],"key_text":[]},{"field_name":"INVOICE_NUMBER","value_id":[19],"value_text":"4249a3bd-82e4-4a22-abbf-c3fb1c170c00","key_id":[],"key_text":[]},{"field_name":"INVOICE_DATE","value_id":[20],"value_text":"22.04.2001","key_id":[],"key_text":[]},{"field_name":"TOTAL_AMOUNT","value_id":[38],"value_text":"745,089","key_id":[],"key_text":[]}],"global_attributes": {"file_id":"20220117_610.png"}}