{"text_boxes":[{"id":1,"text":"Ghana ","bbox":[313,40,30,12]},{"id":2,"text":"D-98693 ","bbox":[353,52,30,12]},{"id":3,"text":"Sofia ","bbox":[405,32,30,12]},{"id":4,"text":"Parkway ","bbox":[437,49,30,12]},{"id":5,"text":"Mountain ","bbox":[486,55,30,12]},{"id":6,"text":"View","bbox":[541,24,30,12]},{"id":7,"text":"Ghana","bbox":[327,26,74,12]},{"id":8,"text":"491625","bbox":[327,30,87,12]},{"id":9,"text":"Plovdiv","bbox":[327,29,100,12]},{"id":10,"text":"Tzar ","bbox":[327,19,113,12]},{"id":11,"text":"Boris","bbox":[346,19,113,12]},{"id":12,"text":"Zero ","bbox":[30,28,30,15]},{"id":13,"text":"Overhead ","bbox":[58,57,30,15]},{"id":14,"text":"Industries ","bbox":[115,57,30,15]},{"id":15,"text":"SE","bbox":[172,12,30,15]},{"id":16,"text":"Adesso ","bbox":[30,57,74,15]},{"id":17,"text":"Bulgaria ","bbox":[87,64,74,15]},{"id":18,"text":"EOOD","bbox":[151,41,74,15]},{"id":19,"text":"Invoice:","bbox":[30,38,155,11]},{"id":20,"text":"52b9184a-8327-4846-87de-a0bd04f59a50","bbox":[78,264,155,14]},{"id":21,"text":"21.02.2001","bbox":[501,64,155,12]},{"id":22,"text":"Price ","bbox":[30,33,199,13]},{"id":23,"text":"(EUR)","bbox":[63,31,199,13]},{"id":24,"text":"Qty","bbox":[208,19,199,13]},{"id":25,"text":"Total ","bbox":[386,31,199,13]},{"id":26,"text":"Item ","bbox":[417,28,199,13]},{"id":27,"text":"Price","bbox":[445,30,199,13]},{"id":28,"text":"9,825","bbox":[30,27,228,12]},{"id":29,"text":"0,852","bbox":[208,27,228,12]},{"id":30,"text":"8,858","bbox":[386,27,228,12]},{"id":31,"text":"9,444","bbox":[30,27,251,12]},{"id":32,"text":"1,225","bbox":[208,27,251,12]},{"id":33,"text":"5,516","bbox":[386,27,251,12]},{"id":34,"text":"7,777","bbox":[30,27,274,12]},{"id":35,"text":"0,189","bbox":[208,27,274,12]},{"id":36,"text":"9,584","bbox":[386,27,274,12]},{"id":37,"text":"2,662","bbox":[30,27,297,12]},{"id":38,"text":"1,354","bbox":[208,27,297,12]},{"id":39,"text":"9,965","bbox":[386,27,297,12]},{"id":40,"text":"3,474","bbox":[30,27,320,12]},{"id":41,"text":"7,346","bbox":[208,27,320,12]},{"id":42,"text":"0,956","bbox":[386,27,320,12]},{"id":43,"text":"4,355","bbox":[30,27,343,12]},{"id":44,"text":"1,316","bbox":[208,27,343,12]},{"id":45,"text":"1,607","bbox":[386,27,343,12]},{"id":46,"text":"0,565","bbox":[30,27,366,12]},{"id":47,"text":"6,631","bbox":[208,27,366,12]},{"id":48,"text":"2,125","bbox":[386,27,366,12]},{"id":49,"text":"3,163","bbox":[30,27,389,12]},{"id":50,"text":"1,494","bbox":[208,27,389,12]},{"id":51,"text":"1,272","bbox":[386,27,389,12]},{"id":52,"text":"Total ","bbox":[30,31,431,13]},{"id":53,"text":"(USD)","bbox":[61,33,431,13]},{"id":54,"text":"775,125","bbox":[104,39,431,13]}],"fields":[{"field_name":"SENDER_ADDRESS","value_id":[1,2,3,4,5,6],"value_text":"Ghana D-98693 Sofia Parkway Mountain View","key_id":[],"key_text":[]},{"field_name":"RECEIVER_ADDRESS","value_id":[7,8,9,10,11],"value_text":"Ghana 491625 Plovdiv Tzar Boris","key_id":[],"key_text":[]},{"field_name":"SENDER_NAME","value_id":[12,13,14,15],"value_text":"Zero Overhead Industries SE","key_id":[],"key_text":[]},{"field_name":"RECEIVER_NAME","value_id":[16,17,18],"value_text":"Adesso Bulgaria EOOD","key_id":[],"key_text":[]},{"field_name":"INVOICE_NUMBER","value_id":[20],"value_text":"52b9184a-8327-4846-87de-a0bd04f59a50","key_id":[],"key_text":[]},{"field_name":"INVOICE_DATE","value_id":[21],"value_text":"21.02.2001","key_id":[],"key_text":[]},{"field_name":"TOTAL_AMOUNT","value_id":[54],"value_text":"775,125","key_id":[],"key_text":[]}],"global_attributes": {"file_id":"20220117_1173.png"}}